{
    "parameters": [
        {
            "model": "umrr11/umrr96",
            "name": "tx_antenna_idx",
            "comment": "Index of Transmit Antenna (UMRR11 : 0 and 1 are ACC, 2 is AEB)",
            "min": 0,
            "max": 2,
            "default": 2
        },
        {
            "model": "umrr11/umrr96",
            "name": "center_frequency_idx",
            "type": "u8",
            "comment": "Index of center frequency (UMRR11: 0..3 in ACC selectable. In AEB mode values 2 and 3 are similar to 1.)",
            "min": 0,
            "max": 3,
            "default": 0
        },
        {   
            "model": "umrr11/umrr96",
            "name": "frequency_sweep_idx",
            "comment": "Index of sweep (UMRR11: currently always 0 because only one sweep for every TX-antenna. UMRR96: 0=226MHz, 1=512MHz, 2=1536MHz)",
            "min": 0,
            "max": 2,
            "default": 0
        },
        {   
            "model": "umrr11",
            "name": "enable_tx_ant_toggle",
            "comment": "Automatic toggle of TX-Antenna 0->2->0 every radar cycle",
            "min": 0,
            "max": 1,
            "default": 0
        },
        {   
            "model": "umrr11",
            "name": "angular_separation",
            "comment": "0 = Disable Angular Separation, 1 = Enable Angular Separation",
            "min": 0,
            "max": 1,
            "default": 0
        },
        {   
            "model": "umrr96",
            "name": "range_toggle_mode",
            "comment": "Automatic toggle of range:0=off, 1=Short-Med, 2=Short-Long, 3=Med-Long",
            "min": 0,
            "max": 3,
            "default": 0
        },
        {
            "name": "ip_source_address",
            "comment": "IP source address (32bit)",
            "default": 3232238347
        }
    ]
}